{
  "kind": "singleType",
  "collectionName": "navigations",
  "info": {
    "singularName": "navigation",
    "pluralName": "navigations",
    "displayName": "Navigation"
  },
  "options": {
    "draftAndPublish": false
  },
  "pluginOptions": {},
  "attributes": {
    "navLinkItems": {
      "type": "component",
      "repeatable": true,
      "component": "navigation-blocks.nav-link-item"
    },
    "navButtons": {
      "type": "component",
      "repeatable": true,
      "component": "navigation-blocks.nav-button"
    }
  }
}
